setup.py
django_fate/__init__.py
django_fate.egg-info/PKG-INFO
django_fate.egg-info/SOURCES.txt
django_fate.egg-info/dependency_links.txt
django_fate.egg-info/top_level.txt
django_fate/api_views/__init__.py
django_fate/api_views/api_view.py
django_fate/filters/__init__.py
django_fate/filters/fields.py
django_fate/filters/filters.py
django_fate/forms/__init__.py
django_fate/forms/form_validator.py
django_fate/forms/pick_form.py
django_fate/paginator/__init__.py
django_fate/paginator/paginator.py
django_fate/paginator/paginator_base.py
django_fate/serializers/__init__.py
django_fate/serializers/fields.py
django_fate/serializers/serializers.py