Metadata-Version: 2.1
Name: django-fate
Version: 0.30
Summary: Django项目中使用的简易API模块
Home-page: https://www.leetab.com
Author: Ryan
Author-email: 604729765@qq.com
License: UNKNOWN
Platform: UNKNOWN
